{
  "id": "a202c9eb-0fd9-4b78-a6b6-dd68ba344064",
  "prevId": "215bebb5-86c9-45b2-b511-314daae8907b",
  "version": "7",
  "dialect": "postgresql",
  "tables": {
    "public.pokemons": {
      "name": "pokemons",
      "schema": "",
      "columns": {
        "id": {
          "name": "id",
          "type": "serial",
          "primaryKey": true,
          "notNull": true
        },
        "pokeid": {
          "name": "pokeid",
          "type": "integer",
          "primaryKey": false,
          "notNull": true
        },
        "name": {
          "name": "name",
          "type": "text",
          "primaryKey": false,
          "notNull": true
        }
      },
      "indexes": {},
      "foreignKeys": {},
      "compositePrimaryKeys": {},
      "uniqueConstraints": {}
    }
  },
  "enums": {},
  "schemas": {},
  "_meta": {
    "columns": {},
    "schemas": {},
    "tables": {}
  }
}